{
  "tweetCount": 771,
  "img": "http://www.bing.com/cr?IG=BF6092FEE57D49FCACAA0B10B4B4ED5C&CID=31D02C307F446FD2167E25E57E756E95&rd=1&h=lkLdQoNX97lsDkWjMgB8bju2Lkire4AO8jGKKwfV9Ac&v=1&r=http%3a%2f%2frealitywives.net%2fblogs%2fwp-content%2fuploads%2f2013%2f10%2fTara-Wallace-LHHNY.png&p=DevEx,5008.1",
  "trendName": "LHHNY",
  "emotions": [
    {
      "count": 55,
      "name": "happy"
    },
    {
      "count": 39,
      "name": "lit"
    },
    {
      "count": 82,
      "name": "sad"
    },
    {
      "count": 10,
      "name": "mad"
    },
    {
      "count": 215,
      "name": "funny"
    }
  ],
  "totalEmojis": 557,
  "maxRetweets": 1894,
  "emojis": [
    {
      "count": 6,
      "char": "\ud83d\ude33"
    },
    {
      "count": 1,
      "char": "\ud83d\ude06"
    },
    {
      "count": 3,
      "char": "\ud83d\ude10"
    },
    {
      "count": 3,
      "char": "\ud83c\udf7f"
    },
    {
      "count": 15,
      "char": "\ud83d\ude4c"
    },
    {
      "count": 3,
      "char": "\ud83d\ude42"
    },
    {
      "count": 3,
      "char": "\u2764"
    },
    {
      "count": 12,
      "char": "\ud83d\ude01"
    },
    {
      "count": 28,
      "char": "\ud83d\ude0d"
    },
    {
      "count": 5,
      "char": "\ud83d\ude18"
    },
    {
      "count": 12,
      "char": "\ud83d\udc4f"
    },
    {
      "count": 3,
      "char": "\ud83d\udca9"
    },
    {
      "count": 3,
      "char": "\ud83d\ude0c"
    },
    {
      "count": 4,
      "char": "\ud83d\ude11"
    },
    {
      "count": 3,
      "char": "\ud83d\udcfa"
    },
    {
      "count": 16,
      "char": "\ud83d\udc80"
    },
    {
      "count": 31,
      "char": "\ud83d\ude44"
    },
    {
      "count": 3,
      "char": "\ud83d\udc36"
    },
    {
      "count": 14,
      "char": "\ud83d\udcaa"
    },
    {
      "count": 7,
      "char": "\ud83d\ude2d"
    },
    {
      "count": 8,
      "char": "\ud83d\ude12"
    },
    {
      "count": 3,
      "char": "\ud83d\ude31"
    },
    {
      "count": 3,
      "char": "\ud83c\udf78"
    },
    {
      "count": 3,
      "char": "\ud83d\ude1b"
    },
    {
      "count": 9,
      "char": "\ud83e\udd14"
    },
    {
      "count": 3,
      "char": "\ud83d\ude0a"
    },
    {
      "count": 12,
      "char": "\ud83d\ude1c"
    },
    {
      "count": 4,
      "char": "\ud83c\udffd"
    },
    {
      "count": 166,
      "char": "\ud83d\ude02"
    },
    {
      "count": 3,
      "char": "\ud83d\udde3"
    },
    {
      "count": 29,
      "char": "\ud83d\ude29"
    },
    {
      "count": 6,
      "char": "\ud83d\ude2c"
    },
    {
      "count": 18,
      "char": "\ud83c\udffb"
    },
    {
      "count": 12,
      "char": "\ud83d\ude2a"
    },
    {
      "count": 14,
      "char": "\ud83c\udffe"
    },
    {
      "count": 1,
      "char": "\u2757"
    },
    {
      "count": 2,
      "char": "\u26b0"
    },
    {
      "count": 3,
      "char": "\ud83d\udc4c"
    },
    {
      "count": 14,
      "char": "\ud83e\udd17"
    },
    {
      "count": 2,
      "char": "\ud83d\ude36"
    },
    {
      "count": 3,
      "char": "\u2639"
    },
    {
      "count": 1,
      "char": "\ud83d\ude45"
    },
    {
      "count": 6,
      "char": "\ud83d\ude08"
    },
    {
      "count": 3,
      "char": "\u270b"
    },
    {
      "count": 9,
      "char": "\ud83d\udd25"
    },
    {
      "count": 45,
      "char": "\ud83d\ude1d"
    }
  ],
  "mostPopTweet": "RT @materialgirl_me: Who agrees that Cardi needs her own show. \ud83d\ude02 #LHHNY https://t.co/vq7P3spXSO"
}